web3cat/data/__init__.py
web3cat/data/chainlink/__init__.py
web3cat/data/chainlink/chainlink_data.py
web3cat/data/chainlink/oracle_aggregator.abi.json
web3cat/data/chainlink/oracle_proxy.abi.json
web3cat/data/chainlink/oracles.json
web3cat/data/core.py
web3cat/data/erc20s/__init__.py
web3cat/data/erc20s/erc20_data.py
web3cat/data/ethers/__init__.py
web3cat/data/ethers/ether_data.py
web3cat/data/gearbox/__init__.py
web3cat/data/gearbox/abi/account_factory_abi.json
web3cat/data/gearbox/abi/credit_account_abi.json
web3cat/data/gearbox/abi/credit_facade_abi.json
web3cat/data/gearbox/abi/credit_manager_abi.json
web3cat/data/gearbox/abi/data_compressor_abi.json
web3cat/data/gearbox/gearbox_data.py
web3cat/data/portfolios/__init__.py
web3cat/data/portfolios/portfolio.py
web3cat/fetcher/__init__.py
web3cat/fetcher/balances/__init__.py
web3cat/fetcher/balances/balance.py
web3cat/fetcher/balances/repo.py
web3cat/fetcher/balances/service.py
web3cat/fetcher/blocks/__init__.py
web3cat/fetcher/blocks/block.py
web3cat/fetcher/blocks/repo.py
web3cat/fetcher/blocks/service.py
web3cat/fetcher/calls/__init__.py
web3cat/fetcher/calls/call.py
web3cat/fetcher/calls/repo.py
web3cat/fetcher/calls/service.py
web3cat/fetcher/core.py
web3cat/fetcher/erc20_metas/__init__.py
web3cat/fetcher/erc20_metas/erc20_abi.json
web3cat/fetcher/erc20_metas/erc20_meta.py
web3cat/fetcher/erc20_metas/repo.py
web3cat/fetcher/erc20_metas/service.py
web3cat/fetcher/erc20_metas/tokens.json
web3cat/fetcher/events/__init__.py
web3cat/fetcher/events/event.py
web3cat/fetcher/events/repo.py
web3cat/fetcher/events/service.py
web3cat/fetcher/events_indices/__init__.py
web3cat/fetcher/events_indices/bitarray.py
web3cat/fetcher/events_indices/constants.py
web3cat/fetcher/events_indices/index.py
web3cat/fetcher/events_indices/index_data.py
web3cat/fetcher/events_indices/repo.py
web3cat/fetcher/utils.py
web3cat/view/__init__.py
web3cat/view/view.py
web3cat/view/wireframes/__init__.py
web3cat/view/wireframes/abstract.py
web3cat-0.1.8.dist-info/LICENSE.md
web3cat-0.1.8.dist-info/WHEEL
web3cat-0.1.8.dist-info/METADATA
web3cat-0.1.8.dist-info/RECORD
