Metadata-Version: 2.1
Name: web3cat
Version: 0.1.8
Summary: Data visualization for EVM-based blockchains
License: MIT
Author: Mono6
Author-email: monowhile6@gmail.com
Requires-Python: >=3.10,<4.0
Classifier: License :: OSI Approved :: MIT License
Classifier: Programming Language :: Python :: 3
Classifier: Programming Language :: Python :: 3.10
Classifier: Programming Language :: Python :: 3.11
Requires-Dist: bokeh (>=2.4.3,<3.0.0)
Requires-Dist: jupyter-bokeh (>=3.0.5,<4.0.0)
Requires-Dist: numpy (>=1.23.3,<2.0.0)
Requires-Dist: polars (>=0.16.16,<0.17.0)
Requires-Dist: web3 (>=6.0.0,<7.0.0)
